etap2pcap/__init__.py
etap2pcap/__main__.py
etap2pcap/common.py
etap2pcap/etap.py
etap2pcap/libusb.py
etap2pcap/main.py
etap2pcap/pcap.py
etap2pcap-0.0.2.dist-info/LICENSE
etap2pcap-0.0.2.dist-info/METADATA
etap2pcap-0.0.2.dist-info/WHEEL
etap2pcap-0.0.2.dist-info/entry_points.txt
etap2pcap-0.0.2.dist-info/top_level.txt
etap2pcap-0.0.2.dist-info/RECORD
