Metadata-Version: 2.1
Name: etap2pcap
Version: 0.0.2
Summary: Tibbo Ethernet Tap pcap logger
Home-page: https://github.com/bozokopic/etap2pcap
License: GPLv3
Platform: UNKNOWN
Classifier: Programming Language :: Python :: 3
Classifier: License :: OSI Approved :: GNU General Public License v3 (GPLv3)
License-File: LICENSE
